README.rst
setup.py
fforms/__init__.py
fforms/cache.py
fforms/fields.py
fforms/schema.py
fforms/validators.py
fforms.egg-info/PKG-INFO
fforms.egg-info/SOURCES.txt
fforms.egg-info/dependency_links.txt
fforms.egg-info/top_level.txt