Metadata-Version: 1.1
Name: fforms
Version: 1.1.1
Summary: Standalone HTML form validation library
Home-page: https://github.com/felipeochoa/fforms
Author: Felipe Ochoa
Author-email: felipeochoa@find-me-on-github.com
License: MIT
Keywords: forms form html
Platform: UNKNOWN
Classifier: Development Status :: 5 - Production/Stable
Classifier: Intended Audience :: Developers
Classifier: Operating System :: OS Independent
Classifier: Programming Language :: Python :: 3 :: Only
Classifier: License :: OSI Approved :: MIT License
